qib/__init__.py
qib/algorithms/__init__.py
qib/algorithms/qubitization/__init__.py
qib/algorithms/qubitization/eigenvalue_transformation.py
qib/algorithms/qubitization/projector_controlled_phase_shift.py
qib/algorithms/vqe/__init__.py
qib/algorithms/vqe/optimizer.py
qib/algorithms/vqe/vqe.py
qib/algorithms/vqe/ansatz/__init__.py
qib/algorithms/vqe/ansatz/ansatz.py
qib/circuit/__init__.py
qib/circuit/circuit.py
qib/field/__init__.py
qib/field/field.py
qib/field/particle.py
qib/lattice/__init__.py
qib/lattice/abstract_lattice.py
qib/lattice/brick_lattice.py
qib/lattice/customized_lattice.py
qib/lattice/fully_connected_lattice.py
qib/lattice/hexagonal_lattice.py
qib/lattice/integer_lattice.py
qib/lattice/layered_lattice.py
qib/lattice/odd_face_centered_lattice.py
qib/lattice/shifted_lattice_convention.py
qib/lattice/triangular_lattice.py
qib/operator/__init__.py
qib/operator/abstract_operator.py
qib/operator/fermi_hubbard_hamiltonian.py
qib/operator/field_operator.py
qib/operator/gates.py
qib/operator/heisenberg_hamiltonian.py
qib/operator/ising_hamiltonian.py
qib/operator/molecular_hamiltonian.py
qib/operator/pauli_operator.py
qib/tensor_network/__init__.py
qib/tensor_network/contraction_tree.py
qib/tensor_network/symbolic_network.py
qib/tensor_network/tensor_network.py
qib/transform/__init__.py
qib/transform/compact_encoding.py
qib/transform/jordan_wigner_encoding.py
qib/transform/parity_encoding.py
qib/util/__init__.py
qib/util/util.py
qib-0.1.0.dist-info/LICENSE
qib-0.1.0.dist-info/METADATA
qib-0.1.0.dist-info/WHEEL
qib-0.1.0.dist-info/top_level.txt
qib-0.1.0.dist-info/RECORD
