Metadata-Version: 2.1
Name: qib
Version: 0.1.0
Summary: Python package for quantum circuits and algorithms
Author: TUM Quantum Computing Group
License: Apache-2.0
Project-URL: Homepage, https://github.com/qc-tum/qib
Requires-Python: >=3.7
License-File: LICENSE
Requires-Dist: numpy
Requires-Dist: scipy
